openbharatocr/__init__.py
openbharatocr/ocr/__init__.py
openbharatocr/ocr/aadhaar.py
openbharatocr/ocr/api.py
openbharatocr/ocr/birth_certificate.py
openbharatocr/ocr/common.py
openbharatocr/ocr/degree.py
openbharatocr/ocr/driving_licence.py
openbharatocr/ocr/pan.py
openbharatocr/ocr/passbook.py
openbharatocr/ocr/passport.py
openbharatocr/ocr/vehicle_registration.py
openbharatocr/ocr/voter_id.py
openbharatocr/ocr/water_bill.py
openbharatocr/unit_tests/__init__.py
openbharatocr/unit_tests/test_aadhaar.py
openbharatocr/unit_tests/test_degree.py
openbharatocr/unit_tests/test_licence.py
openbharatocr/unit_tests/test_pan.py
openbharatocr/unit_tests/test_passbook.py
openbharatocr/unit_tests/test_voter.py
openbharatocr-0.4.3.dist-info/LICENSE
openbharatocr-0.4.3.dist-info/METADATA
openbharatocr-0.4.3.dist-info/WHEEL
openbharatocr-0.4.3.dist-info/top_level.txt
openbharatocr-0.4.3.dist-info/RECORD
