Metadata-Version: 2.1
Name: openbharatocr
Version: 0.4.3
Summary: openbharatocr is an opensource python library for ocr Indian government documents
Home-page: https://github.com/essentiasoftserv/openbharatocr
Author: essentiasoftserv
Author-email: kunal@essentia.dev
License: Apache
Requires-Python: >=3.6
License-File: LICENSE
Requires-Dist: pytesseract ==0.3.10
Requires-Dist: opencv-python ==4.6.0.66
Requires-Dist: easyocr ==1.7.1
Requires-Dist: numpy ==1.26.4
